zencache/__init__.py
zencache/server.py
zencache/service.py
zencache-0.1.4.dist-info/LICENSE
zencache-0.1.4.dist-info/METADATA
zencache-0.1.4.dist-info/WHEEL
zencache-0.1.4.dist-info/entry_points.txt
zencache-0.1.4.dist-info/top_level.txt
zencache-0.1.4.dist-info/RECORD
